dekcli-0.1.35.dist-info/METADATA
dekcli-0.1.35.dist-info/WHEEL
dekcli-0.1.35.dist-info/entry_points.txt
dekcli/__init__.py
dekcli/click/__entry__.py
dekcli/click/__init__.py
dekcli/click/gitea.py
dekcli/click/k8s/__init__.py
dekcli/click/k8s/base/__init__.py
dekcli/click/k8s/base/django.py
dekcli/click/k8s/dekspider.py
dekcli/click/k8s/djcreator.py
dekcli/click/pybuild.py
dekcli/click/smb.py
dekcli/click/v2ray.py
dekcli/core/__init__.py
dekcli/core/git/__init__.py
dekcli/core/git/ref.py
dekcli/core/git/repo.py
dekcli/core/k8s/__init__.py
dekcli/core/k8s/core.py
dekcli/core/nuitka/__init__.py
dekcli/core/nuitka/core.py
dekcli/core/pyinstaller/__init__.py
dekcli/core/pyinstaller/core.py
dekcli/core/pyinstaller/templatefiles/project/.pyinstaller.spec-tpl
dekcli/core/pyinstaller/tmpl.py
dekcli/core/smb/__init__.py
dekcli/core/smb/core.py
dekcli/core/v2ray/__init__.py
dekcli/core/v2ray/server.pysh
dekcli/utils/__init__.py
dekcli/utils/progress.py
dekcli-0.1.35.dist-info/RECORD
