Metadata-Version: 2.1
Name: dekcli
Version: 0.1.35
Author-Email: sanzenwin <sanzenwin@gmail.com>
License: MIT
Requires-Python: <3.13,>=3.10
Requires-Dist: GitPython<=3.1.41
Requires-Dist: kubernetes<=29.0.0
Requires-Dist: smbprotocol<=1.10.1
Requires-Dist: pyinstaller<=6.8.0
Requires-Dist: tqdm<=4.66.4
Requires-Dist: toml<=0.10.2
Requires-Dist: qrcode<=8.2
Requires-Dist: dektools[version,win32,ymal]<1.0.0
Requires-Dist: deksecrets<1.0.0
Requires-Dist: dekgen<1.0.0
Requires-Dist: dekvenv<1.0.0
Requires-Dist: dekmedia[svg]<1.0.0
